[
    {
        "title": "SQL Server String Functions",
        "text": [
            ""
        ],
        "examples": [],
        "tables": []
    },
    {
        "title": "SQL Server Math/Numeric Functions",
        "text": [],
        "examples": [],
        "tables": []
    },
    {
        "title": "SQL Server Date Functions",
        "text": [],
        "examples": [],
        "tables": []
    },
    {
        "title": "SQL Server Advanced Functions",
        "text": [
            "❮ Previous\nNext ❯"
        ],
        "examples": [],
        "tables": []
    }
]